plover_websocket_server/__init__.py
plover_websocket_server/config.py
plover_websocket_server/errors.py
plover_websocket_server/listens.py
plover_websocket_server/manager.py
plover_websocket_server/server.py
plover_websocket_server/websocket/__init__.py
plover_websocket_server/websocket/app_keys.py
plover_websocket_server/websocket/approval_dialog.py
plover_websocket_server/websocket/server.py
plover_websocket_server/websocket/views.py
plover_websocket_server-0.1.13.dist-info/licenses/LICENSE.txt
plover_websocket_server-0.1.13.dist-info/METADATA
plover_websocket_server-0.1.13.dist-info/WHEEL
plover_websocket_server-0.1.13.dist-info/entry_points.txt
plover_websocket_server-0.1.13.dist-info/top_level.txt
plover_websocket_server-0.1.13.dist-info/zip-safe
plover_websocket_server-0.1.13.dist-info/RECORD
