Metadata-Version: 2.4
Name: plover_websocket_server
Version: 0.1.13
Summary: A server for exposing Plover engine events and functionality
Author-email: Daniel de Souza <daniel@cosmicdna.co.uk>
License-Expression: GPL-3.0-or-later
Project-URL: Homepage, https://github.com/CosmicDNA/plover-websocket-server.git
Keywords: plover plover_plugin websocket steno stenography
Classifier: Development Status :: 4 - Beta
Classifier: Environment :: Plugins
Classifier: Intended Audience :: End Users/Desktop
Classifier: Operating System :: OS Independent
Classifier: Programming Language :: Python :: 3.8
Classifier: Programming Language :: Python :: 3.9
Classifier: Programming Language :: Python :: 3.10
Classifier: Programming Language :: Python :: 3.11
Classifier: Programming Language :: Python :: 3.12
Requires-Python: >=3.8
License-File: LICENSE.txt
Requires-Dist: plover>=4.0.0.dev8
Requires-Dist: aiohttp
Requires-Dist: aiohttp_middlewares
Requires-Dist: jsonpickle
Requires-Dist: nacl_middleware
Requires-Dist: PySide6
Provides-Extra: test
Requires-Dist: pytest; extra == "test"
Provides-Extra: dev
Requires-Dist: plover_websocket_server[test]; extra == "dev"
Requires-Dist: pre-commit; extra == "dev"
Requires-Dist: build; extra == "dev"
Requires-Dist: bump-my-version; extra == "dev"
Requires-Dist: twine; extra == "dev"
Requires-Dist: ruff; extra == "dev"
Dynamic: license-file
